gklearn/__init__.py
gklearn/dataset/__init__.py
gklearn/dataset/data_fetcher.py
gklearn/dataset/dataset.py
gklearn/dataset/file_managers.py
gklearn/dataset/graph_synthesizer.py
gklearn/dataset/metadata.py
gklearn/examples/__init__.py
gklearn/examples/ged/__init__.py
gklearn/examples/ged/compute_graph_edit_distance.py
gklearn/examples/kernels/__init__.py
gklearn/examples/kernels/compute_distance_in_kernel_space.py
gklearn/examples/kernels/compute_graph_kernel.py
gklearn/examples/kernels/compute_graph_kernel_old.py
gklearn/examples/kernels/model_selection_old.py
gklearn/examples/preimage/__init__.py
gklearn/examples/preimage/median_preimege_generator.py
gklearn/examples/preimage/median_preimege_generator_cml.py
gklearn/examples/preimage/median_preimege_generator_py.py
gklearn/experiments/__init__.py
gklearn/experiments/my_new_test_file.py
gklearn/experiments/taskhub.py
gklearn/experiments/kernels/__init__.py
gklearn/experiments/kernels/kernel_models_implementations/__init__.py
gklearn/experiments/kernels/kernel_models_implementations/run_wlsubtree.py
gklearn/ged/__init__.py
gklearn/ged/edit_costs/__init__.py
gklearn/ged/edit_costs/constant.py
gklearn/ged/edit_costs/edit_cost.py
gklearn/ged/env/__init__.py
gklearn/ged/env/common_types.py
gklearn/ged/env/ged_data.py
gklearn/ged/env/ged_env.py
gklearn/ged/env/node_map.py
gklearn/ged/learning/__init__.py
gklearn/ged/learning/cost_matrices_learner.py
gklearn/ged/learning/costs_learner.py
gklearn/ged/median/__init__.py
gklearn/ged/median/median_graph_estimator.py
gklearn/ged/median/median_graph_estimator_cml.py
gklearn/ged/median/median_graph_estimator_py.py
gklearn/ged/median/test_median_graph_estimator.py
gklearn/ged/median/utils.py
gklearn/ged/methods/__init__.py
gklearn/ged/methods/bipartite.py
gklearn/ged/methods/ged_method.py
gklearn/ged/methods/lsape_based_method.py
gklearn/ged/model/__init__.py
gklearn/ged/model/distances.py
gklearn/ged/model/ged_com.py
gklearn/ged/model/ged_model.py
graphkit_learn-0.2.1.post20240206154638.dist-info/LICENSE
graphkit_learn-0.2.1.post20240206154638.dist-info/METADATA
graphkit_learn-0.2.1.post20240206154638.dist-info/WHEEL
graphkit_learn-0.2.1.post20240206154638.dist-info/top_level.txt
graphkit_learn-0.2.1.post20240206154638.dist-info/RECORD
