Metadata-Version: 2.1
Name: graphkit-learn
Version: 0.2.1.post20240206154638
Summary: A Python library for graph kernels, graph edit distances, and graph pre-images
Home-page: https://github.com/jajupmochi/graphkit-learn
Author: Linlin Jia
Author-email: linlin.jia@unibe.ch
License: UNKNOWN
Project-URL: Documentation, https://graphkit-learn.readthedocs.io
Project-URL: Source, https://github.com/jajupmochi/graphkit-learn
Project-URL: Tracker, https://github.com/jajupmochi/graphkit-learn/issues
Platform: UNKNOWN
Classifier: Programming Language :: Python :: 3
Classifier: License :: OSI Approved :: GNU General Public License v3 (GPLv3)
Classifier: Operating System :: OS Independent
Classifier: Intended Audience :: Science/Research
Classifier: Intended Audience :: Developers
Requires-Dist: numpy >=1.16.2
Requires-Dist: scipy >=1.1.0
Requires-Dist: matplotlib >=3.1.0
Requires-Dist: networkx >=2.2
Requires-Dist: scikit-learn >=1.1.0
Requires-Dist: tabulate >=0.8.2
Requires-Dist: tqdm >=4.26.0
Requires-Dist: control >=0.8.2
Requires-Dist: cvxopt >=1.2.5
Requires-Dist: mosek >=9.2.5 ; python_version >= "3.6"
